loan_risk_predictor/__init__.py
loan_risk_predictor/data_preprocessing.py
loan_risk_predictor/model.py
loan_risk_predictor/train.py
loan_risk_predictor-0.2.2.dist-info/licenses/LICENSE
loan_risk_predictor-0.2.2.dist-info/METADATA
loan_risk_predictor-0.2.2.dist-info/WHEEL
loan_risk_predictor-0.2.2.dist-info/entry_points.txt
loan_risk_predictor-0.2.2.dist-info/top_level.txt
loan_risk_predictor-0.2.2.dist-info/RECORD
