Metadata-Version: 2.4
Name: loan-risk-predictor
Version: 0.2.2
Summary: A package to predict loan risk using a decision tree model.
Author-email: Shanujan Suresh <shanujansh@gmail.com>
License-Expression: MIT
Project-URL: Homepage, https://github.com/shanujans/loan-risk-prediction
Project-URL: Bug Tracker, https://github.com/shanujans/loan-risk-prediction/issues
Classifier: Programming Language :: Python :: 3
Classifier: Operating System :: OS Independent
Requires-Python: >=3.7
License-File: LICENSE
Requires-Dist: pandas
Requires-Dist: numpy
Requires-Dist: scikit-learn
Dynamic: license-file
